{
    "configSchemaVersion": "1.0.2",
    "api": {
        "cookie_secret": "p2FAdrUN3tac",
        "host": "localhost",
        "metric": {
            "cors_white_list": [
                "*"
            ]
        },
        "mode": "dev",
        "port": 8888,
        "ssl": false,
        "websocketKeepAliveDelayInSeconds": 0
    },
    "db": {
        "mongodb": {
            "main": "localhost:27017"
        },
        "pgres": {
            "main": "postgresql://prodiguer_db_user:@localhost/prodiguer"
        }
    },
    "mail": {
        "imap": {
            "host": "courriel3.ipsl.jussieu.fr",
            "mailbox": "AMPQ-PROD",
            "mailbox_processed": "AMPQ-PROD-PROCESSED",
            "password": "XXXXXXXXX",
            "port": 993,
            "username": "superviseur"
        },
        "smtp": {
            "addresses": {
                "prodiguer": "superviseur@ipsl.jussieu.fr",
                "supervisor": "superviseur@ipsl.jussieu.fr"
            },
            "host": "courriel3.ipsl.jussieu.fr",
            "password": "XXXXXXXXX",
            "port": 587,
            "username": "superviseur"
        }
    },
    "mq": {
        "connections": {
            "libigcm": "amqp://libigcm-mq-user:XXXXXXXXX@localhost:5672/prodiguer?connection_attempts=3&heartbeat_interval=3600",
            "main": "amqp://prodiguer-mq-user:XXXXXXXXX@localhost:5672/prodiguer?connection_attempts=3&heartbeat_interval=3600"
        }
    }
}